rcm/__init__.py
rcm/_version.py
rcm/datacollectors/__init__.py
rcm/datacollectors/pandas_collector.py
rcm/dcm/__init__.py
rcm/dcm/random_location.py
rcm/initialization/__init__.py
rcm/initialization/base_init.py
rcm/initialization/random_init.py
rcm/model/__init__.py
rcm/model/household_agent.py
rcm/model/households_first_activation.py
rcm/model/location_agent.py
rcm/model/location_model.py
rcm/model/model.py
rcm/satisfaction/__init__.py
rcm/satisfaction/random_satisfaction.py
rcm/util/__init__.py
rcm/util/polygon_utils.py
rcm/visualization/__init__.py
rcm/visualization/gui.py
rcm/visualization/map.py
tests/__init__.py
tests/fixtures.py
tests/test_model.py
rcm-0.1.0.dist-info/LICENSE
rcm-0.1.0.dist-info/METADATA
rcm-0.1.0.dist-info/WHEEL
rcm-0.1.0.dist-info/top_level.txt
rcm-0.1.0.dist-info/RECORD
