Metadata-Version: 2.1
Name: rcm
Version: 0.1.0
Summary: Library for geo-spatial multi-agent models.
Home-page: https://gitlab.computationalscience.nl/dynaslum/residential-choice-model
Author: Berend Weel, Debraj Roy
Author-email: b.weel@esiencecenter.nl
License: Apache Software License
Platform: any
Classifier: Programming Language :: Python
Classifier: Programming Language :: Python :: 3
Classifier: Programming Language :: Python :: 3.5
Classifier: Programming Language :: Python :: 3.6
Classifier: Development Status :: 3 - Alpha
Classifier: Natural Language :: English
Classifier: Intended Audience :: Developers
Classifier: License :: OSI Approved :: Apache Software License
Classifier: Operating System :: OS Independent
Classifier: Topic :: Software Development :: Libraries :: Python Modules
Requires-Dist: shapely
Requires-Dist: pyproj
Requires-Dist: osmnx
Requires-Dist: numpy
Requires-Dist: Mesa
Requires-Dist: mesa-geo
Provides-Extra: dev
Requires-Dist: isort ; extra == 'dev'
Requires-Dist: pycodestyle ; extra == 'dev'
Requires-Dist: pyflakes ; extra == 'dev'
Requires-Dist: pytest ; extra == 'dev'
Requires-Dist: pytest-cov ; extra == 'dev'
Requires-Dist: pytest-flake8 ; extra == 'dev'
Requires-Dist: pytest-html ; extra == 'dev'
Provides-Extra: notebooks
Requires-Dist: jupyter ; extra == 'notebooks'
Requires-Dist: matplotlib ; extra == 'notebooks'
Requires-Dist: nblint ; extra == 'notebooks'
